AUTHORS.rst
CONTRIBUTING.rst
HISTORY.rst
LICENSE
MANIFEST.in
README.rst
requirements.txt
requirements_dev.txt
setup.cfg
setup.py
docs/Makefile
docs/authors.rst
docs/conf.py
docs/contributing.rst
docs/history.rst
docs/index.rst
docs/installation.rst
docs/make.bat
docs/modules.rst
docs/readme.rst
docs/tyluigiutils.hadoop.rst
docs/tyluigiutils.rst
docs/tyluigiutils.spark.rst
docs/usage.rst
docs/_build/html/_static/ajax-loader.gif
docs/_build/html/_static/comment-bright.png
docs/_build/html/_static/comment-close.png
docs/_build/html/_static/comment.png
docs/_build/html/_static/down-pressed.png
docs/_build/html/_static/down.png
docs/_build/html/_static/file.png
docs/_build/html/_static/minus.png
docs/_build/html/_static/plus.png
docs/_build/html/_static/up-pressed.png
docs/_build/html/_static/up.png
docs/source/modules.rst
docs/source/tyluigiutils.rst
tests/__init__.py
tests/test_tyluigiutils.py
tyluigiutils/__init__.py
tyluigiutils/external.py
tyluigiutils/hadoop.py
tyluigiutils/path.py
tyluigiutils/spark.py
tyluigiutils/sqoop.py
tyluigiutils/url.py
tyluigiutils.egg-info/PKG-INFO
tyluigiutils.egg-info/SOURCES.txt
tyluigiutils.egg-info/dependency_links.txt
tyluigiutils.egg-info/not-zip-safe
tyluigiutils.egg-info/requires.txt
tyluigiutils.egg-info/top_level.txt