Metadata-Version: 1.1
Name: tyluigiutils
Version: 0.2.0
Summary: Misc Luigi related code used by TrustYou 
Home-page: https://github.com/mfcabrera/tyluigiutils
Author: Miguel Cabrera
Author-email: mfcabrera@gmail.com
License: MIT license
Keywords: tyluigiutils
Platform: UNKNOWN
Classifier: Development Status :: 2 - Pre-Alpha
Classifier: Intended Audience :: Developers
Classifier: License :: OSI Approved :: MIT License
Classifier: Natural Language :: English
Classifier: Programming Language :: Python :: 2
Classifier: Programming Language :: Python :: 2.7
Classifier: Programming Language :: Python :: 3
Classifier: Programming Language :: Python :: 3.3
Classifier: Programming Language :: Python :: 3.4
Classifier: Programming Language :: Python :: 3.5
